[
  {
    "id": 1,
    "title": "Show 1 ",
    "description": "Experience True Taste",
    "cta": "Book Tickets",
    "image": "/images/image1.jpg",
    "background": "bg-yellow-500"
  },
  {
    "id": 2,
    "title": "Show 2",
    "description": "Experience True Fear",
    "cta": "Book Tickets",
    "image": "/images/image2.jpg",
    "background": "bg-gray-900"
  },
  {
    "id": 3,
    "title": "Theatre 1",
    "description": "Experience True Tears",
    "cta": "Book Tickets",
    "image": "/images/image3.jpg",
    "background": "bg-gray-700"
  },
  {
    "id": 4,
    "title": "Theatre 2",
    "description": "Experience True Thrill",
    "cta": "Book Tickets",
    "image": "/images/image4.jpg",
    "background": "bg-blue-900"
  }
]